{
    "vendor_code": "Not Found in Documents",
    "contact_person": "Not Found in Documents",
    "mobile_number": "Not Found in Documents",
    "email_id": "htindia@gmail.com, info@htindia.in",
    "emd_applicability": "Not Found in Documents",
    "emd_details": "Not Found in Documents",
    "emd_exemption_reason": "Not Found in Documents",
    "mse_preference_applicability": "Not Found in Documents",
    "mse_preference_applied_in_gem": "Not Found in Documents",
    "udyam_number": "Not Found in Documents",
    "mse_category": "Not Found in Documents",
    "mse_pp_verification": "Not Found in Documents",
    "mse_purchase_preference_eligibility": "Not Found in Documents",
    "mii_preference_applicability": "Not Found in Documents",
    "mii_preference_applied_in_gem": "Not Found in Documents",
    "mii_local_content_declaration": "Not Found in Documents",
    "local_content_percentage": "Not Found in Documents",
    "mii_purchase_preference_eligibility": "Not Found in Documents",
    "integrity_pact": "Not Found in Documents",
    "confidentiality_clause_declaration": "Yes",
    "holiday_listing_declaration": "NIL",
    "land_border_sharing_declaration": "Yes",
    "nil_deviations_declaration": "Not Found in Documents",
    "details_of_deviations": [],
    "deviations_acceptance": "Not Found in Documents",
    "validity": "Not Found in Documents",
    "gst_number": "Not Found in Documents",
    "gst_filing_status": "Not Found in Documents",
    "blacklisted_in_cpcl_mopng": "No",
    "query_to_be_raised": [],
    "commercial_evaluation_status": "Not Found in Documents",
    "reason_for_rejection": "Not Found in Documents"
}